AUTHORS
CHANGELOG.txt
DESCRIPTION
LICENSE
MANIFEST.in
README.rst
setup.py
django_privacy.egg-info/PKG-INFO
django_privacy.egg-info/SOURCES.txt
django_privacy.egg-info/dependency_links.txt
django_privacy.egg-info/top_level.txt
privacy/__init__.py
privacy/admin.py
privacy/forms.py
privacy/models.py
privacy/migrations/0001_initial.py
privacy/migrations/__init__.py
privacy/templates/privacy/partials/field.html
privacy/templatetags/__init__.py
privacy/templatetags/privacy_tags.py
privacy/tests/__init__.py
privacy/tests/factories.py
privacy/tests/forms_tests.py
privacy/tests/models_tests.py
privacy/tests/runtests.py
privacy/tests/south_settings.py
privacy/tests/tags_tests.py
privacy/tests/test_settings.py
privacy/tests/urls.py
privacy/tests/test_app/__init__.py
privacy/tests/test_app/admin.py
privacy/tests/test_app/factories.py
privacy/tests/test_app/forms.py
privacy/tests/test_app/models.py
privacy/tests/test_app/privacy_settings.py
privacy/tests/test_app/templates/404.html
privacy/tests/test_app/templates/base.html
privacy/tests/test_app/templates/test_app/dummyprofilemodel_form.html