Metadata-Version: 1.0
Name: django-privacy
Version: 0.1
Summary: Reusable Django app to add privacy settings to fields and/or objects.
Home-page: https://github.com/bitmazk/django-privacy
Author: Tobias Lorenz
Author-email: tobias.lorenz@bitmazk.com
License: The MIT License
Keywords: django,reusable,privacy,setting
Platform: OS Independent
